lightlabel/__init__.py
lightlabel/db/__init__.py
lightlabel/db/base.py
lightlabel/db/mongodb.py
lightlabel/exceptions/__init__.py
lightlabel/plan/__init__.py
lightlabel/projects/__init__.py
lightlabel/projects/text_classification.py
lightlabel/tasks/__init__.py
lightlabel/tasks/base.py
lightlabel/tools/__init__.py
lightlabel/web/__init__.py
lightlabel/web/engine.py
lightLabel-0.1.0.dist-info/LICENSE
lightLabel-0.1.0.dist-info/METADATA
lightLabel-0.1.0.dist-info/WHEEL
lightLabel-0.1.0.dist-info/top_level.txt
lightLabel-0.1.0.dist-info/RECORD
