Metadata-Version: 2.1
Name: lightLabel
Version: 0.1.0
Summary: lightsmile's nlp label library
Home-page: https://github.com/smilelight/lightLabel
Author: lightsmile
Author-email: iamlightsmile@gmail.com
License: Apache-2.0
Platform: UNKNOWN
Classifier: Development Status :: 4 - Beta
Classifier: Operating System :: OS Independent
Classifier: Intended Audience :: Developers
Classifier: Programming Language :: Python
Classifier: Programming Language :: Python :: 3
Classifier: Programming Language :: Python :: 3.6
Classifier: Programming Language :: Python :: 3.7
Classifier: Topic :: Software Development :: Libraries
Requires-Dist: pymongo
Requires-Dist: tqdm
Requires-Dist: flask
Requires-Dist: flask-cors
Requires-Dist: flask-restful
Requires-Dist: lightutils
